nfilepicker/__init__.py
nfilepicker-1.0.2.dist-info/LICENSE
nfilepicker-1.0.2.dist-info/METADATA
nfilepicker-1.0.2.dist-info/WHEEL
nfilepicker-1.0.2.dist-info/top_level.txt
nfilepicker-1.0.2.dist-info/RECORD
