Metadata-Version: 2.1
Name: nfilepicker
Version: 1.0.2
Summary: A Python package that creates a file/folder chooser with ncurses.
Home-page: https://github.com/Python3-8/nfilepicker
Author: Pranav Balaji Pooruli
Author-email: pranav.pooruli@gmail.com
License: MIT
Platform: UNKNOWN
Classifier: License :: OSI Approved :: MIT License
Classifier: Programming Language :: Python :: 3
Classifier: Programming Language :: Python :: 3.9
Requires-Dist: pick
